better_fnmatch-0.1.1.dist-info/METADATA
better_fnmatch-0.1.1.dist-info/WHEEL
better_fnmatch-0.1.1.dist-info/licenses/LICENSE
better_fnmatch/__init__.py
better_fnmatch/better_fnmatch.cpython-314t-darwin.so
better_fnmatch/better_fnmatch.pyi
better_fnmatch/py.typed
better_fnmatch-0.1.1.dist-info/RECORD
