Metadata-Version: 2.4
Name: better-fnmatch
Version: 0.1.1
Classifier: Programming Language :: Rust
Classifier: Programming Language :: Python :: Implementation :: CPython
Classifier: Programming Language :: Python :: Implementation :: PyPy
License-File: LICENSE
Summary: A featureful fnmatch implementation
License-Expression: EUPL-1.2
Requires-Python: >=3.10
Project-URL: Homepage, https://vlaci.github.io/better-fnmatch
Project-URL: Repository, https://github.com/vlaci/better-fnmatch
Project-URL: Changelog, https://github.com/vlaci/better-fnmatch/blob/main/CHANGELOG.md
